fastapi_users_db_mongodb/__init__.py
fastapi_users_db_mongodb/access_token.py
fastapi_users_db_mongodb/py.typed
fastapi_users_db_mongodb-1.1.0.dist-info/LICENSE
fastapi_users_db_mongodb-1.1.0.dist-info/WHEEL
fastapi_users_db_mongodb-1.1.0.dist-info/METADATA
fastapi_users_db_mongodb-1.1.0.dist-info/RECORD
