Metadata-Version: 2.1
Name: fastapi-users-db-mongodb
Version: 1.1.0
Summary: FastAPI Users database adapter for MongoDB.
Home-page: https://github.com/fastapi-users/fastapi-users-db-mongodb
Author: François Voron
Author-email: fvoron@gmail.com
Requires-Python: >=3.7
Classifier: License :: OSI Approved :: MIT License
Classifier: Development Status :: 5 - Production/Stable
Classifier: Framework :: AsyncIO
Classifier: Intended Audience :: Developers
Classifier: Programming Language :: Python :: 3.7
Classifier: Programming Language :: Python :: 3.8
Classifier: Programming Language :: Python :: 3.9
Classifier: Programming Language :: Python :: 3 :: Only
Classifier: Topic :: Internet :: WWW/HTTP :: Session
Requires-Dist: fastapi-users >= 9.1.0
Requires-Dist: motor >=2.5.1,<3.0.0
Project-URL: Documentation, https://fastapi-users.github.io/fastapi-users
